sklearn_deltatfidf/__init__.py
sklearn_deltatfidf-0.3.dist-info/LICENSE.txt
sklearn_deltatfidf-0.3.dist-info/METADATA
sklearn_deltatfidf-0.3.dist-info/WHEEL
sklearn_deltatfidf-0.3.dist-info/top_level.txt
sklearn_deltatfidf-0.3.dist-info/RECORD
