Metadata-Version: 1.1
Name: sklearn-deltatfidf
Version: 0.3
Summary: DeltaTfidfVectorizer for scikit-learn
Home-page: https://github.com/r-m-n/sklearn-deltatfidf
Author: UNKNOWN
Author-email: UNKNOWN
License: MIT
Download-URL: https://github.com/r-m-n/sklearn-deltatfidf/archive/0.3.tar.gz
Keywords: sklearn,scikit-learn,tfidf,deltatfidf,delta tfidf
Platform: UNKNOWN
